kg_nodeexporter/__init__.py
kg_nodeexporter/builder.py
kg_nodeexporter/option.py
kg_nodeexporter/py.typed
kg_nodeexporter/tests/__init__.py
kg_nodeexporter/tests/test_builder.py
tests/__init__.py
tests/test_builder.py
kg_nodeexporter-0.8.0.dist-info/LICENSE
kg_nodeexporter-0.8.0.dist-info/METADATA
kg_nodeexporter-0.8.0.dist-info/WHEEL
kg_nodeexporter-0.8.0.dist-info/top_level.txt
kg_nodeexporter-0.8.0.dist-info/RECORD
